pkgver/__init__.py
scora_ldap/__init__.py
scora_ldap/main.py
scora_ldap/database/__init__.py
scora_ldap/database/dynamodb.py
scora_ldap/resources/__init__.py
scora_ldap/resources/custom_logger_formatter.py
scora_ldap/resources/ldap.py
scora_ldap/resources/service.py
scora_ldap/utils/__init__.py
scora_ldap/utils/constants.py
scora_ldap/utils/misc.py
scora_ldap-0.1.0.dist-info/LICENSE
scora_ldap-0.1.0.dist-info/METADATA
scora_ldap-0.1.0.dist-info/WHEEL
scora_ldap-0.1.0.dist-info/top_level.txt
scora_ldap-0.1.0.dist-info/zip-safe
scora_ldap-0.1.0.dist-info/RECORD
