Metadata-Version: 2.1
Name: scora-ldap
Version: 0.1.0
Summary: Scora Ldap
Home-page: https://github.com/oncase/scora-ldap
Author: Oncase
Author-email: contato@oncase.com.br
Maintainer: Guilherme Morone
Maintainer-email: guilherme.morone@oncase.com.br
License: MIT
Keywords: scora
Classifier: Intended Audience :: Developers
Classifier: Natural Language :: English
Classifier: Programming Language :: Python :: 3.11
Requires-Python: >=3.8
License-File: LICENSE
Requires-Dist: ldap3 (>=2.9.1)
Requires-Dist: boto3 (>=1.26.57)
Requires-Dist: numpy (>=1.24.1)
